commonroad_crime/__init__.py
commonroad_crime/__version__.py
commonroad_crime/data_structure/__init__.py
commonroad_crime/data_structure/base.py
commonroad_crime/data_structure/configuration.py
commonroad_crime/data_structure/crime_interface.py
commonroad_crime/data_structure/scene.py
commonroad_crime/data_structure/type.py
commonroad_crime/measure/__init__.py
commonroad_crime/measure/acceleration/__init__.py
commonroad_crime/measure/acceleration/a_lat_req.py
commonroad_crime/measure/acceleration/a_long_req.py
commonroad_crime/measure/acceleration/a_req.py
commonroad_crime/measure/acceleration/dst.py
commonroad_crime/measure/distance/__init__.py
commonroad_crime/measure/distance/dce.py
commonroad_crime/measure/distance/hw.py
commonroad_crime/measure/distance/msd.py
commonroad_crime/measure/distance/psd.py
commonroad_crime/measure/index/__init__.py
commonroad_crime/measure/index/aci.py
commonroad_crime/measure/index/btn.py
commonroad_crime/measure/index/ci.py
commonroad_crime/measure/index/cpi.py
commonroad_crime/measure/index/pri.py
commonroad_crime/measure/index/rss.py
commonroad_crime/measure/index/soi.py
commonroad_crime/measure/index/stn.py
commonroad_crime/measure/index/tci.py
commonroad_crime/measure/jerk/__init__.py
commonroad_crime/measure/jerk/lat_j.py
commonroad_crime/measure/jerk/long_j.py
commonroad_crime/measure/potential/__init__.py
commonroad_crime/measure/potential/pf.py
commonroad_crime/measure/potential/sp.py
commonroad_crime/measure/probability/__init__.py
commonroad_crime/measure/probability/p_mc.py
commonroad_crime/measure/probability/p_smh.py
commonroad_crime/measure/probability/p_srs.py
commonroad_crime/measure/reachable_set/__init__.py
commonroad_crime/measure/reachable_set/drivable_area.py
commonroad_crime/measure/time/__init__.py
commonroad_crime/measure/time/ags.py
commonroad_crime/measure/time/et.py
commonroad_crime/measure/time/pet.py
commonroad_crime/measure/time/pttc.py
commonroad_crime/measure/time/tc.py
commonroad_crime-0.4.4.dist-info/licenses/LICENSE
commonroad_crime-0.4.4.dist-info/METADATA
commonroad_crime-0.4.4.dist-info/WHEEL
commonroad_crime-0.4.4.dist-info/top_level.txt
commonroad_crime-0.4.4.dist-info/RECORD
