Metadata-Version: 2.4
Name: commonroad-crime
Version: 0.4.4
Summary: criticality measures of automated vehicles
Home-page: https://commonroad.in.tum.de/tools/commonroad-crime
Author: Technical University of Munich
Author-email: commonroad@lists.lrz.de
License: BSD 3-Clause
Project-URL: Documentation, https://cps.pages.gitlab.lrz.de/commonroad/commonroad-criticality-measures/
Project-URL: Forum, https://github.com/CommonRoad/commonroad-crime/issues
Project-URL: Source, https://github.com/CommonRoad/commonroad-crime
Keywords: criticality,autonomous driving
Classifier: Programming Language :: C++
Classifier: Programming Language :: Python :: 3.10
Classifier: Programming Language :: Python :: 3.11
Classifier: License :: OSI Approved :: BSD License
Classifier: Operating System :: POSIX :: Linux
License-File: LICENSE
Requires-Dist: commonroad-io~=2024.1
Requires-Dist: commonroad-vehicle-models~=3.0.0
Requires-Dist: commonroad-route-planner~=2025.1.0
Requires-Dist: commonroad-drivability-checker~=2025.3.1
Requires-Dist: commonroad-reach~=2025.2.0
Requires-Dist: commonroad-clcs~=2025.2.0
Requires-Dist: matplotlib<3.9,>=3.5.2
Requires-Dist: numpy>=1.19.0
Requires-Dist: scipy>=1.7.3
Requires-Dist: shapely<3.0.0,>=2.0.1
Requires-Dist: omegaconf>=2.1.1
Requires-Dist: casadi>=3.6.3
Requires-Dist: tqdm>=4.65.0
Requires-Dist: imageio>=2.9.0
Requires-Dist: pytest>=7.4.0
Dynamic: author
Dynamic: author-email
Dynamic: classifier
Dynamic: description
Dynamic: description-content-type
Dynamic: home-page
Dynamic: keywords
Dynamic: license
Dynamic: license-file
Dynamic: project-url
Dynamic: requires-dist
Dynamic: summary
